MrSnippets/__init__.py
MrSnippets/__version__.py
MrSnippets/data_converters.py
MrSnippets/data_mining.py
MrSnippets/data_support.py
MrSnippets/image_processing.py
MrSnippets/mongo_wrapper.py
MrSnippets/mysql_wrapper.py
MrSnippets/nlp.py
MrSnippets/sql_wrapper.py
MrSnippets/utilities.py
MrSnippets/web_client.py
MrSnippets-2.0.1.dist-info/LICENSE.md
MrSnippets-2.0.1.dist-info/METADATA
MrSnippets-2.0.1.dist-info/WHEEL
MrSnippets-2.0.1.dist-info/top_level.txt
MrSnippets-2.0.1.dist-info/RECORD
