Metadata-Version: 2.1
Name: MrSnippets
Version: 2.0.1
Summary: A complete collection of commonly used code Snippets in Python
Home-page: https://github.com/dhamodharanrk/MrSnippets
Author: Dhamodharan Karuppuswamy
Author-email: dhamodharanrk@gmail.com
License: BSD 2-Clause
Platform: UNKNOWN
Classifier: License :: OSI Approved :: BSD License
Classifier: Programming Language :: Python
Classifier: Programming Language :: Python :: 2.7
Classifier: Programming Language :: Python :: 3.4
Classifier: Programming Language :: Python :: 3.5
Classifier: Programming Language :: Python :: 3.6
Classifier: Programming Language :: Python :: 3.7
Classifier: Programming Language :: Python :: 3.8
Requires-Dist: beautifulsoup4 (>=4.3.3)
Requires-Dist: requests (>=2.18.4)
Requires-Dist: html5lib (>=1.0b10)
Requires-Dist: user-agent (>=0.1.9)
Requires-Dist: selenium (>=3.141.0)
Requires-Dist: PyMySQL (>=0.9.3)
Requires-Dist: pymongo (>=3.8.0)
Requires-Dist: ftfy (>=5.5.1)
Requires-Dist: tldextract (>=2.2.1)
Requires-Dist: bleach (>=3.1.0)
Requires-Dist: python-csv (>=0.0.11)
Requires-Dist: nltk (>=3.4.5)
Requires-Dist: spacy (>=2.3.2)
Requires-Dist: sklearn (>=0.0)
Requires-Dist: pytest-shutil (>=1.6.0)
Requires-Dist: Pillow (>=2.2.1)
Requires-Dist: pyodbc (>=4.0.26)
Requires-Dist: fuzzywuzzy (>=0.18.0)
Requires-Dist: pycountry (>=19.8)
Requires-Dist: geopy (>=1.21)
Requires-Dist: python-dateutil (>=2.8.1)
Requires-Dist: urllib3 (>=1.25)
Requires-Dist: tldextract (>=2.2.2)
Requires-Dist: geotext (>=0.4.0)
Requires-Dist: dateparser (>=1.0.0)
Requires-Dist: uuid (>=1.30)
Requires-Dist: glob2 (>=0.7)
